LICENSE
MANIFEST.in
README.md
setup.cfg
setup.py
supermark/__init__.py
supermark/base.py
supermark/breadcrumbs.py
supermark/build_doc.py
supermark/build_html.py
supermark/build_latex.py
supermark/chunks.py
supermark/code.py
supermark/command.py
supermark/config.py
supermark/core.py
supermark/examples_yaml.py
supermark/extend.py
supermark/icons.py
supermark/pagemap.py
supermark/pandoc.py
supermark/parse.py
supermark/placeholder.py
supermark/report.py
supermark/setup.py
supermark/utils.py
supermark/write_html.py
supermark/write_md.py
supermark.egg-info/PKG-INFO
supermark.egg-info/SOURCES.txt
supermark.egg-info/dependency_links.txt
supermark.egg-info/entry_points.txt
supermark.egg-info/requires.txt
supermark.egg-info/top_level.txt
supermark/data/__init__.py
supermark/data/bootstrap-icons.svg
supermark/doc/__init__.py
supermark/doc/development.md
supermark/doc/index.md
supermark/doc/installation.md
supermark/doc/usage.md
supermark/doc/writing.md
supermark/extensions/__init__.py
supermark/extensions/abstract/__init__.py
supermark/extensions/abstract/abstract.css
supermark/extensions/abstract/doc.md
supermark/extensions/abstract/example-00.md
supermark/extensions/boxes/__init__.py
supermark/extensions/boxes/boxes.css
supermark/extensions/boxes/doc.md
supermark/extensions/boxes/example-00.md
supermark/extensions/boxes/example-01.md
supermark/extensions/boxes/example-02.md
supermark/extensions/boxes/example-10.md
supermark/extensions/boxes/example-20.md
supermark/extensions/boxes/example-30.md
supermark/extensions/boxes/example-40.md
supermark/extensions/boxes/example-50.md
supermark/extensions/boxes/example-60.md
supermark/extensions/button/__init__.py
supermark/extensions/button/button.css
supermark/extensions/button/doc.md
supermark/extensions/button/example-00.md
supermark/extensions/button/example-01.md
supermark/extensions/card/__init__.py
supermark/extensions/card/card.css
supermark/extensions/card/doc.md
supermark/extensions/card/example-00.md
supermark/extensions/card/example-01.md
supermark/extensions/card/example-02.md
supermark/extensions/card/example-03.md
supermark/extensions/card/example-04.md
supermark/extensions/card/example-05.md
