Metadata-Version: 2.1
Name: supermark
Version: 0.3.24
Summary: Pandoc-based transformation tool for documents containing different markup languages.
Home-page: https://github.com/falkr/supermark
Download-URL: https://github.com/falkr/supermark/archive/0.2.tar.gz
Author: Frank Alexander Kraemer
Author-email: kraemer.frank@gmail.com
License: GPLv3
Keywords: education
Classifier: Development Status :: 3 - Alpha
Classifier: Intended Audience :: Education
Classifier: Programming Language :: Python :: 3.7
Classifier: Programming Language :: Python :: 3.8
Classifier: Programming Language :: Python :: 3.9
Classifier: Programming Language :: Python :: 3.10
License-File: LICENSE
